{
  "dailyReadData": {
    "1768649729044": {
      "filePath": "",
      "openCount": 0,
      "fileId": "1768649729044",
      "duration": 48000
    },
    "undefined": {
      "filePath": "",
      "openCount": 0,
      "duration": 72000
    },
    "1768706057050": {
      "filePath": "",
      "openCount": 0,
      "fileId": "1768706057050",
      "duration": 240000
    },
    "1768649141047": {
      "filePath": "",
      "openCount": 0,
      "fileId": "1768649141047",
      "duration": 84000
    },
    "1768469600770": {
      "filePath": "",
      "openCount": 0,
      "fileId": "1768469600770",
      "duration": 18000
    },
    "1768654589050": {
      "filePath": "",
      "openCount": 0,
      "fileId": "1768654589050",
      "duration": 30000
    },
    "1768479037631": {
      "filePath": "",
      "openCount": 0,
      "fileId": "1768479037631",
      "duration": 6000
    },
    "1768559267711": {
      "filePath": "",
      "openCount": 0,
      "fileId": "1768559267711",
      "duration": 6000
    },
    "1768554509723": {
      "filePath": "",
      "openCount": 0,
      "fileId": "1768554509723",
      "duration": 300000
    },
    "1768555985704": {
      "filePath": "",
      "openCount": 0,
      "fileId": "1768555985704",
      "duration": 372000
    },
    "1768707011050": {
      "filePath": "",
      "openCount": 0,
      "fileId": "1768707011050",
      "duration": 300000
    },
    "1768707041045": {
      "filePath": "",
      "openCount": 0,
      "fileId": "1768707041045",
      "duration": 1242000
    },
    "1768707107045": {
      "filePath": "",
      "openCount": 0,
      "fileId": "1768707107045",
      "duration": 156000
    },
    "1768707131049": {
      "filePath": "",
      "openCount": 0,
      "fileId": "1768707131049",
      "duration": 348000
    },
    "1768707257040": {
      "filePath": "",
      "openCount": 0,
      "fileId": "1768707257040",
      "duration": 6000
    },
    "1768540841711": {
      "filePath": "",
      "openCount": 0,
      "fileId": "1768540841711",
      "duration": 6000
    },
    "1768651649061": {
      "filePath": "",
      "openCount": 0,
      "fileId": "1768651649061",
      "duration": 138000
    },
    "1768707551055": {
      "filePath": "",
      "openCount": 0,
      "fileId": "1768707551055",
      "duration": 18000
    },
    "1768707623049": {
      "filePath": "",
      "openCount": 0,
      "fileId": "1768707623049",
      "duration": 576000
    },
    "1768707869049": {
      "filePath": "",
      "openCount": 0,
      "fileId": "1768707869049",
      "duration": 66000
    },
    "1768707947059": {
      "filePath": "",
      "openCount": 0,
      "fileId": "1768707947059",
      "duration": 18000
    },
    "1768707995040": {
      "filePath": "",
      "openCount": 0,
      "fileId": "1768707995040",
      "duration": 36000
    },
    "1768708073051": {
      "filePath": "",
      "openCount": 0,
      "fileId": "1768708073051",
      "duration": 30000
    },
    "1768708133051": {
      "filePath": "",
      "openCount": 0,
      "fileId": "1768708133051",
      "duration": 72000
    }
  }
}