{
  "dailyReadData": {
    "1768556171707": {
      "filePath": "",
      "openCount": 0,
      "fileId": "1768556171707",
      "duration": 6000
    },
    "1768820414597": {
      "filePath": "",
      "openCount": 0,
      "fileId": "1768820414597",
      "duration": 1524000
    },
    "1768805305769": {
      "filePath": "",
      "openCount": 0,
      "fileId": "1768805305769",
      "duration": 6000
    },
    "1768806685766": {
      "filePath": "",
      "openCount": 0,
      "fileId": "1768806685766",
      "duration": 6000
    },
    "1768708133051": {
      "filePath": "",
      "openCount": 0,
      "fileId": "1768708133051",
      "duration": 12000
    },
    "1768797817776": {
      "filePath": "",
      "openCount": 0,
      "fileId": "1768797817776",
      "duration": 6000
    },
    "1768718219006": {
      "filePath": "",
      "openCount": 0,
      "fileId": "1768718219006",
      "duration": 12000
    },
    "1768555985704": {
      "filePath": "",
      "openCount": 0,
      "fileId": "1768555985704",
      "duration": 18000
    },
    "1768707041045": {
      "filePath": "",
      "openCount": 0,
      "fileId": "1768707041045",
      "duration": 72000
    },
    "1768707011050": {
      "filePath": "",
      "openCount": 0,
      "fileId": "1768707011050",
      "duration": 24000
    },
    "1768479037631": {
      "filePath": "",
      "openCount": 0,
      "fileId": "1768479037631",
      "duration": 78000
    },
    "undefined": {
      "filePath": "",
      "openCount": 0,
      "duration": 12000
    },
    "1768972117937": {
      "filePath": "",
      "openCount": 0,
      "fileId": "1768972117937",
      "duration": 6000
    },
    "1768972225936": {
      "filePath": "",
      "openCount": 0,
      "fileId": "1768972225936",
      "duration": 42000
    },
    "1768756241242": {
      "filePath": "",
      "openCount": 0,
      "fileId": "1768756241242",
      "duration": 12000
    },
    "1768917338279": {
      "filePath": "",
      "openCount": 0,
      "fileId": "1768917338279",
      "duration": 66000
    }
  }
}